scar_add_metadata_toolbox/__init__.py
scar_add_metadata_toolbox/classes.py
scar_add_metadata_toolbox/commands.py
scar_add_metadata_toolbox/config.py
scar_add_metadata_toolbox/csw.py
scar_add_metadata_toolbox/hazmat/__init__.py
scar_add_metadata_toolbox/hazmat/csw.py
scar_add_metadata_toolbox/hazmat/metadata.py
scar_add_metadata_toolbox/static/css/app.css
scar_add_metadata_toolbox/static/css/map.css
scar_add_metadata_toolbox/static/js/app.js
scar_add_metadata_toolbox/static/js/feedback.js
scar_add_metadata_toolbox/static/js/item.js
scar_add_metadata_toolbox/static/txt/heartbeat.txt
scar_add_metadata_toolbox/static/xsl/iso-html/displayElement.xsl
scar_add_metadata_toolbox/static/xsl/iso-html/elements-ISO.xml
scar_add_metadata_toolbox/static/xsl/iso-html/headers-ISO.xml
scar_add_metadata_toolbox/static/xsl/iso-html/printFormatted.xsl
scar_add_metadata_toolbox/static/xsl/iso-html/printTextLines.xsl
scar_add_metadata_toolbox/static/xsl/iso-html/xml-to-html-ISO.xsl
scar_add_metadata_toolbox/static/xsl/iso-html/xml-to-text-ISO.xsl
scar_add_metadata_toolbox/static/xsl/iso-rubric/isoRubricHTML.xsl
scar_add_metadata_toolbox/static/xsl/iso-rubric/isoRubricStars.xsl
scar_add_metadata_toolbox/templates/_includes/collection/item.j2
scar_add_metadata_toolbox/templates/_includes/collection/summary-information.j2
scar_add_metadata_toolbox/templates/_includes/common/header.j2
scar_add_metadata_toolbox/templates/_includes/items/additional-information.j2
scar_add_metadata_toolbox/templates/_includes/items/authors.j2
scar_add_metadata_toolbox/templates/_includes/items/citation.j2
scar_add_metadata_toolbox/templates/_includes/items/contact.j2
scar_add_metadata_toolbox/templates/_includes/items/data-wms-instructions.j2
scar_add_metadata_toolbox/templates/_includes/items/data.j2
scar_add_metadata_toolbox/templates/_includes/items/descriptive-keywords.j2
scar_add_metadata_toolbox/templates/_includes/items/extent.j2
scar_add_metadata_toolbox/templates/_includes/items/licence-cc-by-4-0.j2
scar_add_metadata_toolbox-0.3.0.dist-info/LICENSE.md
scar_add_metadata_toolbox-0.3.0.dist-info/WHEEL
scar_add_metadata_toolbox-0.3.0.dist-info/METADATA
scar_add_metadata_toolbox-0.3.0.dist-info/RECORD
