Metadata-Version: 2.1
Name: scar-add-metadata-toolbox
Version: 0.3.0
Summary: Editor, repository and data catalogue for SCAR Antarctic Digital Database (ADD) discovery metadata
Home-page: https://github.com/antarctica/scar-add-metadata-toolbox
License: OGL-UK-3.0
Author: Felix Fennell
Author-email: felnne@bas.ac.uk
Requires-Python: >=3.6,<4.0
Classifier: Intended Audience :: Science/Research
Classifier: License :: Other/Proprietary License
Classifier: Operating System :: OS Independent
Classifier: Programming Language :: Python :: 3
Classifier: Programming Language :: Python :: 3.6
Classifier: Programming Language :: Python :: 3.7
Classifier: Programming Language :: Python :: 3.8
Classifier: Programming Language :: Python :: 3.9
Requires-Dist: Faker (>=4.1.1,<5.0.0)
Requires-Dist: Flask (>=1.1.1,<2.0.0)
Requires-Dist: Frozen-Flask (>=0.15.0,<0.16.0)
Requires-Dist: Markdown (>=3.2.2,<4.0.0)
Requires-Dist: OWSLib (>=0.19.2,<0.20.0)
Requires-Dist: SQLAlchemy (>=1.3.18,<2.0.0)
Requires-Dist: awscli (>=1.18.93,<2.0.0)
Requires-Dist: backports-datetime-fromisoformat (>=1.0.0,<2.0.0)
Requires-Dist: bas-metadata-library (>=0.4.0,<0.5.0)
Requires-Dist: bas-style-kit-jinja-templates (>=0.5.0,<0.6.0)
Requires-Dist: click-spinner (>=0.1.10,<0.2.0)
Requires-Dist: flask-azure-oauth (>=0.4.1,<0.5.0)
Requires-Dist: importlib_metadata (>=1.7.0,<2.0.0)
Requires-Dist: importlib_resources (>=3.0.0,<4.0.0)
Requires-Dist: inquirer (>=2.7.0,<3.0.0)
Requires-Dist: lxml (==4.5.2)
Requires-Dist: msal (>=1.4.1,<2.0.0)
Requires-Dist: psycopg2-binary (>=2.8.5,<3.0.0)
Requires-Dist: pycsw (>=2.6.0,<3.0.0)
Requires-Dist: pyproj (==2.6.0)
Requires-Dist: python-dateutil (>=2.8.1,<3.0.0)
Requires-Dist: python-dotenv (>=0.10.3,<0.11.0)
Requires-Dist: requests (>=2.24.0,<3.0.0)
Requires-Dist: sentry-sdk[flask] (>=0.14.3,<0.15.0)
Requires-Dist: simplejson (>=3.17.0,<4.0.0)
Requires-Dist: str2bool (>=1.1,<2.0)
Requires-Dist: tabulate (>=0.8.7,<0.9.0)
Project-URL: Repository, https://github.com/antarctica/scar-add-metadata-toolbox
